src/__init__.py
src/bath_operations.py
src/operations.py
pkgfileutils-0.0.1.dist-info/METADATA
pkgfileutils-0.0.1.dist-info/WHEEL
pkgfileutils-0.0.1.dist-info/top_level.txt
pkgfileutils-0.0.1.dist-info/RECORD
