Metadata-Version: 2.1
Name: pkgfileutils
Version: 0.0.1
Summary: DZ Python package
Home-page: http://github.com
Author: User
Author-email: <youremail@email.com>
Keywords: python,dz package
Classifier: Development Status :: 3 - Alpha
Classifier: Intended Audience :: Education
Classifier: Programming Language :: Python :: 2
Classifier: Programming Language :: Python :: 3
Classifier: Operating System :: MacOS :: MacOS X
Classifier: Operating System :: Microsoft :: Windows
